{"name":"Level","position":[0,0,0],"eulerAngles":[0,0,0],"scale":[1,1,1],"exportEntity":false,"children":[{"name":"model_static_obstacle_gate","position":[0,0,-6.7220001220703125],"eulerAngles":[180,0,180],"scale":[1,1,1],"exportEntity":true,"children":[{"name":"model_barrier_001","position":[0,1.7896000146865845,-6.706200122833252],"eulerAngles":[0,0,0],"scale":[1,1,1],"exportEntity":true,"children":[],"type":"mapObject","model":"model_barrier_001","materials":["mat_gate_001.json"]}],"type":"staticObstacle","model":"model_finish_001","materials":["mat_gate_001.json","mat_gate_001_teleport.json"]},{"name":"normal_road_001","position":[0,0,-8.258999824523926],"eulerAngles":[0,0,0],"scale":[1,1,1],"exportEntity":true,"children":[],"contactProcessingThreshold":0,"type":"collisionObject","model":"model_road_001","materials":["mat_road_001.json"]},{"name":"normal_road_002","position":[0,0,-8.241600036621094],"eulerAngles":[0,0,0],"scale":[1,1,1],"exportEntity":true,"children":[{"name":"pipe_head","position":[2,0.5,-0.6729000210762024],"eulerAngles":[180,0,180],"scale":[1,1,1],"exportEntity":true,"children":[],"type":"pipeObject","model":"model_pipe_head","materials":["mat_road_001.json"]},{"name":"pipe_head","position":[-2,0.5,-0.6729000210762024],"eulerAngles":[180,0,180],"scale":[1,1,1],"exportEntity":true,"children":[],"type":"pipeObject","model":"model_pipe_head","materials":["mat_road_001.json"]}],"contactProcessingThreshold":0,"type":"collisionObject","model":"model_road_002","materials":["mat_road_001.json"]},{"name":"normal_road_002","position":[0,0,3.75],"eulerAngles":[0,0,0],"scale":[1,1,1.1952999830245972],"exportEntity":true,"children":[],"contactProcessingThreshold":0,"type":"collisionObject","model":"model_road_002","materials":["mat_road_001.json"]},{"name":"normal_road_002","position":[0,0,17.8710994720459],"eulerAngles":[0,0,0],"scale":[1,1,1.1952999830245972],"exportEntity":true,"children":[],"contactProcessingThreshold":0,"type":"collisionObject","model":"model_road_002","materials":["mat_road_001.json"]},{"name":"normal_road_014","position":[0,0,32.19060134887695],"eulerAngles":[0,0,0],"scale":[1,1,1],"exportEntity":true,"children":[{"name":"normal_pipe_014","position":[2,0.5,32.19060134887695],"eulerAngles":[0,0,0],"scale":[1,1,1],"exportEntity":true,"children":[],"type":"pipeObject","model":"model_pipe_014","materials":["mat_road_001.json"]},{"name":"normal_pipe_014","position":[-2,0.5,32.19060134887695],"eulerAngles":[0,0,0],"scale":[1,1,1],"exportEntity":true,"children":[],"type":"pipeObject","model":"model_pipe_014","materials":["mat_road_001.json"]},{"name":"pipe_head","position":[2,-2.8773999214172363,47.78340148925781],"eulerAngles":[0,0,0],"scale":[1,1,1],"exportEntity":true,"children":[],"type":"pipeObject","model":"model_pipe_head","materials":["mat_road_001.json"]},{"name":"pipe_head","position":[-2,-2.8773999214172363,47.78340148925781],"eulerAngles":[0,0,0],"scale":[1,1,1],"exportEntity":true,"children":[],"type":"pipeObject","model":"model_pipe_head","materials":["mat_road_001.json"]}],"contactProcessingThreshold":0,"type":"collisionObject","model":"model_road_014","materials":["mat_road_001.json"]},{"name":"model_coin_001","position":[-0.6000000238418579,-1.0966999530792236,39.454200744628906],"eulerAngles":[0,0,0],"scale":[1,1,1],"exportEntity":true,"children":[],"type":"coin","model":"model_coin_001","materials":["mat_items_001.json"]},{"name":"model_coin_001","position":[0.6000000238418579,-2.3617000579833984,45.01850128173828],"eulerAngles":[0,0,0],"scale":[1,1,1],"exportEntity":true,"children":[],"type":"coin","model":"model_coin_001","materials":["mat_items_001.json"]},{"name":"model_dynamic_obstacle_box_001","position":[-0.9041000008583069,-2.944000005722046,48.7947998046875],"eulerAngles":[0,0,0],"scale":[0.30000001192092896,0.30000001192092896,0.30000001192092896],"exportEntity":true,"children":[],"type":"boxObstacle","model":"model_box_obstacle_001","materials":["mat_box_obstacle_001.json"]},{"name":"model_dynamic_obstacle_box_001","position":[-0.9041000008583069,-2.3433001041412354,48.7947998046875],"eulerAngles":[0,0,0],"scale":[0.30000001192092896,0.30000001192092896,0.30000001192092896],"exportEntity":true,"children":[],"type":"boxObstacle","model":"model_box_obstacle_001","materials":["mat_box_obstacle_001.json"]},{"name":"model_dynamic_obstacle_box_001","position":[-0.3005000054836273,-2.944000005722046,48.7947998046875],"eulerAngles":[0,0,0],"scale":[0.30000001192092896,0.30000001192092896,0.30000001192092896],"exportEntity":true,"children":[],"type":"boxObstacle","model":"model_box_obstacle_001","materials":["mat_box_obstacle_001.json"]},{"name":"model_dynamic_obstacle_box_001","position":[-0.3005000054836273,-2.3433001041412354,48.7947998046875],"eulerAngles":[0,0,0],"scale":[0.30000001192092896,0.30000001192092896,0.30000001192092896],"exportEntity":true,"children":[],"type":"boxObstacle","model":"model_box_obstacle_001","materials":["mat_box_obstacle_001.json"]},{"name":"model_dynamic_obstacle_box_001","position":[0.30219998955726624,-2.944000005722046,48.7947998046875],"eulerAngles":[0,0,0],"scale":[0.30000001192092896,0.30000001192092896,0.30000001192092896],"exportEntity":true,"children":[],"type":"boxObstacle","model":"model_box_obstacle_001","materials":["mat_box_obstacle_001.json"]},{"name":"model_dynamic_obstacle_box_001","position":[0.30219998955726624,-2.3433001041412354,48.7947998046875],"eulerAngles":[0,0,0],"scale":[0.30000001192092896,0.30000001192092896,0.30000001192092896],"exportEntity":true,"children":[],"type":"boxObstacle","model":"model_box_obstacle_001","materials":["mat_box_obstacle_001.json"]},{"name":"model_dynamic_obstacle_box_001","position":[0.9092000126838684,-2.944000005722046,48.7947998046875],"eulerAngles":[0,0,0],"scale":[0.30000001192092896,0.30000001192092896,0.30000001192092896],"exportEntity":true,"children":[],"type":"boxObstacle","model":"model_box_obstacle_001","materials":["mat_box_obstacle_001.json"]},{"name":"model_dynamic_obstacle_box_001","position":[0.9092000126838684,-2.3433001041412354,48.7947998046875],"eulerAngles":[0,0,0],"scale":[0.30000001192092896,0.30000001192092896,0.30000001192092896],"exportEntity":true,"children":[],"type":"boxObstacle","model":"model_box_obstacle_001","materials":["mat_box_obstacle_001.json"]},{"name":"model_coin_001","position":[-0.6000000238418579,-2.595900058746338,51.81119918823242],"eulerAngles":[0,0,0],"scale":[1,1,1],"exportEntity":true,"children":[],"type":"coin","model":"model_coin_001","materials":["mat_items_001.json"]},{"name":"model_coin_001","position":[0.6000000238418579,-2.3224000930786133,57.96480178833008],"eulerAngles":[0,0,0],"scale":[1,1,1],"exportEntity":true,"children":[],"type":"coin","model":"model_coin_001","materials":["mat_items_001.json"]},{"name":"model_coin_001","position":[0.6000000238418579,-1.8581000566482544,64.51909637451172],"eulerAngles":[0,0,0],"scale":[1,1,1],"exportEntity":true,"children":[],"type":"coin","model":"model_coin_001","materials":["mat_items_001.json"]},{"name":"model_coin_001","position":[-0.6000000238418579,-0.1264999955892563,70.03340148925781],"eulerAngles":[0,0,0],"scale":[1,1,1],"exportEntity":true,"children":[],"type":"coin","model":"model_coin_001","materials":["mat_items_001.json"]},{"name":"model_coin_001","position":[0.6000000238418579,0.7702999711036682,74.99459838867188],"eulerAngles":[0,0,0],"scale":[1,1,1],"exportEntity":true,"children":[],"type":"coin","model":"model_coin_001","materials":["mat_items_001.json"]},{"name":"model_dynamic_obstacle_box_001","position":[-0.9041000008583069,0.30630001425743103,76.89109802246094],"eulerAngles":[0,0,0],"scale":[0.30000001192092896,0.30000001192092896,0.30000001192092896],"exportEntity":true,"children":[],"type":"boxObstacle","model":"model_box_obstacle_001","materials":["mat_box_obstacle_001.json"]},{"name":"model_dynamic_obstacle_box_001","position":[-0.9041000008583069,0.9071000218391418,76.89109802246094],"eulerAngles":[0,0,0],"scale":[0.30000001192092896,0.30000001192092896,0.30000001192092896],"exportEntity":true,"children":[],"type":"boxObstacle","model":"model_box_obstacle_001","materials":["mat_box_obstacle_001.json"]},{"name":"model_dynamic_obstacle_box_001","position":[-0.3005000054836273,0.30630001425743103,76.89109802246094],"eulerAngles":[0,0,0],"scale":[0.30000001192092896,0.30000001192092896,0.30000001192092896],"exportEntity":true,"children":[],"type":"boxObstacle","model":"model_box_obstacle_001","materials":["mat_box_obstacle_001.json"]},{"name":"model_dynamic_obstacle_box_001","position":[-0.3005000054836273,0.9071000218391418,76.89109802246094],"eulerAngles":[0,0,0],"scale":[0.30000001192092896,0.30000001192092896,0.30000001192092896],"exportEntity":true,"children":[],"type":"boxObstacle","model":"model_box_obstacle_001","materials":["mat_box_obstacle_001.json"]},{"name":"model_dynamic_obstacle_box_001","position":[0.30219998955726624,0.30630001425743103,76.89109802246094],"eulerAngles":[0,0,0],"scale":[0.30000001192092896,0.30000001192092896,0.30000001192092896],"exportEntity":true,"children":[],"type":"boxObstacle","model":"model_box_obstacle_001","materials":["mat_box_obstacle_001.json"]},{"name":"model_dynamic_obstacle_box_001","position":[0.30219998955726624,0.9071000218391418,76.89109802246094],"eulerAngles":[0,0,0],"scale":[0.30000001192092896,0.30000001192092896,0.30000001192092896],"exportEntity":true,"children":[],"type":"boxObstacle","model":"model_box_obstacle_001","materials":["mat_box_obstacle_001.json"]},{"name":"model_dynamic_obstacle_box_001","position":[0.9092000126838684,0.30630001425743103,76.89109802246094],"eulerAngles":[0,0,0],"scale":[0.30000001192092896,0.30000001192092896,0.30000001192092896],"exportEntity":true,"children":[],"type":"boxObstacle","model":"model_box_obstacle_001","materials":["mat_box_obstacle_001.json"]},{"name":"model_dynamic_obstacle_box_001","position":[0.9092000126838684,0.9071000218391418,76.89109802246094],"eulerAngles":[0,0,0],"scale":[0.30000001192092896,0.30000001192092896,0.30000001192092896],"exportEntity":true,"children":[],"type":"boxObstacle","model":"model_box_obstacle_001","materials":["mat_box_obstacle_001.json"]},{"name":"normal_road_002","position":[0,-3.244999885559082,47.666900634765625],"eulerAngles":[0,0,0],"scale":[1,1,1],"exportEntity":true,"children":[{"name":"normal_pipe_head","position":[2,-2.744999885559082,52.49250030517578],"eulerAngles":[180,0,180],"scale":[1,1,1],"exportEntity":true,"children":[],"type":"pipeObject","model":"model_pipe_head","materials":["mat_road_001.json"]},{"name":"normal_pipe_head","position":[-2,-2.744999885559082,52.49250030517578],"eulerAngles":[180,0,180],"scale":[1,1,1],"exportEntity":true,"children":[],"type":"pipeObject","model":"model_pipe_head","materials":["mat_road_001.json"]},{"name":"normal_pipe_002","position":[2,-2.744999885559082,52.49020004272461],"eulerAngles":[0,0,0],"scale":[1,1,0.6000000238418579],"exportEntity":true,"children":[],"type":"pipeObject","model":"model_pipe_002","materials":["mat_road_001.json"]},{"name":"normal_pipe_002","position":[-2,-2.744999885559082,52.49020004272461],"eulerAngles":[0,0,0],"scale":[1,1,0.6000000238418579],"exportEntity":true,"children":[],"type":"pipeObject","model":"model_pipe_002","materials":["mat_road_001.json"]}],"contactProcessingThreshold":0,"type":"collisionObject","model":"model_road_002","materials":["mat_road_001.json"]},{"name":"normal_road_014","position":[0,0,75.08409881591797],"eulerAngles":[180,0,180],"scale":[1,1,1],"exportEntity":true,"children":[{"name":"normal_pipe_014","position":[-2,0.6337000131607056,75.08409881591797],"eulerAngles":[180,0,180],"scale":[1,1,1],"exportEntity":true,"children":[],"type":"pipeObject","model":"model_pipe_014","materials":["mat_road_001.json"]},{"name":"normal_pipe_014","position":[2,0.6337000131607056,75.08409881591797],"eulerAngles":[180,0,180],"scale":[1,1,1],"exportEntity":true,"children":[],"type":"pipeObject","model":"model_pipe_014","materials":["mat_road_001.json"]}],"contactProcessingThreshold":0,"type":"collisionObject","model":"model_road_014","materials":["mat_road_001.json"]},{"name":"normal_road_014","position":[0,0,75.08409881591797],"eulerAngles":[0,0,0],"scale":[1,1,1],"exportEntity":true,"children":[{"name":"normal_pipe_014","position":[2,0.6337000131607056,75.08409881591797],"eulerAngles":[0,0,0],"scale":[1,1,1],"exportEntity":true,"children":[],"type":"pipeObject","model":"model_pipe_014","materials":["mat_road_001.json"]},{"name":"normal_pipe_014","position":[-2,0.6337000131607056,75.08409881591797],"eulerAngles":[0,0,0],"scale":[1,1,1],"exportEntity":true,"children":[],"type":"pipeObject","model":"model_pipe_014","materials":["mat_road_001.json"]},{"name":"pipe_head","position":[2,-2.7460999488830566,90.6863021850586],"eulerAngles":[0,0,0],"scale":[1,1,1],"exportEntity":true,"children":[],"type":"pipeObject","model":"model_pipe_head","materials":["mat_road_001.json"]},{"name":"pipe_head","position":[-2,-2.7460999488830566,90.6863021850586],"eulerAngles":[0,0,0],"scale":[1,1,1],"exportEntity":true,"children":[],"type":"pipeObject","model":"model_pipe_head","materials":["mat_road_001.json"]}],"contactProcessingThreshold":0,"type":"collisionObject","model":"model_road_014","materials":["mat_road_001.json"]},{"name":"model_coin_001","position":[-0.6000000238418579,-1.9837000370025635,86.60030364990234],"eulerAngles":[0,0,0],"scale":[1,1,1],"exportEntity":true,"children":[],"type":"coin","model":"model_coin_001","materials":["mat_items_001.json"]},{"name":"model_coin_001","position":[0.6000000238418579,-2.3631999492645264,92.0562973022461],"eulerAngles":[0,0,0],"scale":[1,1,1],"exportEntity":true,"children":[],"type":"coin","model":"model_coin_001","materials":["mat_items_001.json"]},{"name":"model_coin_001","position":[0,-2.3631999492645264,97.51200103759766],"eulerAngles":[0,0,0],"scale":[1,1,1],"exportEntity":true,"children":[],"type":"coin","model":"model_coin_001","materials":["mat_items_001.json"]},{"name":"normal_road_002","position":[0,-3.244999885559082,102.57879638671875],"eulerAngles":[0,0,0],"scale":[1,1,1],"exportEntity":true,"children":[],"contactProcessingThreshold":0,"type":"collisionObject","model":"model_road_002","materials":["mat_road_001.json"]},{"name":"model_coin_001","position":[0,-2.3631999492645264,107.7343978881836],"eulerAngles":[0,0,0],"scale":[1,1,1],"exportEntity":true,"children":[],"type":"coin","model":"model_coin_001","materials":["mat_items_001.json"]},{"name":"model_coin_001","position":[0,-2.3631999492645264,112.78910064697266],"eulerAngles":[0,0,0],"scale":[1,1,1],"exportEntity":true,"children":[],"type":"coin","model":"model_coin_001","materials":["mat_items_001.json"]},{"name":"normal_road_002","position":[0,-3.244999885559082,90.68240356445312],"eulerAngles":[0,0,0],"scale":[1,1,1],"exportEntity":true,"children":[],"contactProcessingThreshold":0,"type":"collisionObject","model":"model_road_002","materials":["mat_road_001.json"]},{"name":"collectable_ball","position":[0,-3.2799999713897705,102.57879638671875],"eulerAngles":[0,0,0],"scale":[1,1,1],"exportEntity":true,"children":[],"type":"collectableBall","model":"model_platform_life_bonus_001","materials":["mat_items_001.json"]},{"name":"normal_road_013","position":[0,-3.244999885559082,114.53949737548828],"eulerAngles":[0,0,0],"scale":[1,1,1],"exportEntity":true,"children":[],"contactProcessingThreshold":0,"type":"collisionObject","model":"model_road_013","materials":["mat_road_001.json"]},{"name":"normal_road_002","position":[0,-6.489999771118164,124.79049682617188],"eulerAngles":[0,0,0],"scale":[1,1,1.5],"exportEntity":true,"children":[{"name":"normal_road_001","position":[0,-6.489999771118164,142.75599670410156],"eulerAngles":[180,0,180],"scale":[1,1,1.5],"exportEntity":true,"children":[],"contactProcessingThreshold":0,"type":"collisionObject","model":"model_road_001","materials":["mat_road_001.json"]},{"name":"obstacle_speed_humps","position":[0,-6.489999771118164,142.26339721679688],"eulerAngles":[0,0,0],"scale":[0.5874999761581421,0.5874999761581421,0.8812999725341797],"exportEntity":true,"children":[],"type":"collisionObject","model":"model_static_obstacle_bump","materials":["mat_items_001.json"]}],"contactProcessingThreshold":0,"type":"collisionObject","model":"model_road_002","materials":["mat_road_001.json"]},{"name":"model_coin_001","position":[0,-5.408400058746338,130.44619750976562],"eulerAngles":[0,0,0],"scale":[1,1,1],"exportEntity":true,"children":[],"type":"coin","model":"model_coin_001","materials":["mat_items_001.json"]},{"name":"model_coin_001","position":[0,-5.408400058746338,136.02430725097656],"eulerAngles":[0,0,0],"scale":[1,1,1],"exportEntity":true,"children":[],"type":"coin","model":"model_coin_001","materials":["mat_items_001.json"]},{"name":"normal_road_002","position":[0,-11.976200103759766,192.5843048095703],"eulerAngles":[180,0,180],"scale":[4,3.6960999965667725,4.353000164031982],"exportEntity":true,"children":[{"name":"normal_road_001","position":[0,-11.976200103759766,192.5843048095703],"eulerAngles":[180,0,180],"scale":[4,3.6960999965667725,4.353000164031982],"exportEntity":true,"children":[],"contactProcessingThreshold":0,"type":"collisionObject","model":"model_road_001","materials":["mat_road_001.json"]},{"name":"normal_road_001","position":[0,-11.976200103759766,140.57069396972656],"eulerAngles":[0,0,0],"scale":[4,3.6960999965667725,4.353000164031982],"exportEntity":true,"children":[],"contactProcessingThreshold":0,"type":"collisionObject","model":"model_road_001","materials":["mat_road_001.json"]}],"contactProcessingThreshold":0,"type":"collisionObject","model":"model_road_002","materials":["mat_road_001.json"]},{"name":"normal_road_002","position":[0,-11.969599723815918,215.18699645996094],"eulerAngles":[180,0,180],"scale":[1,1,1.670699954032898],"exportEntity":true,"children":[{"name":"normal_road_001","position":[0,-11.969599723815918,215.18699645996094],"eulerAngles":[180,0,180],"scale":[1,1,1.670699954032898],"exportEntity":true,"children":[],"contactProcessingThreshold":0,"type":"collisionObject","model":"model_road_001","materials":["mat_road_001.json"]}],"contactProcessingThreshold":0,"type":"collisionObject","model":"model_road_002","materials":["mat_road_001.json"]},{"name":"collectable_ball","position":[0,-12.013899803161621,192.76980590820312],"eulerAngles":[0,0,0],"scale":[1,1,1],"exportEntity":true,"children":[],"type":"collectableBall","model":"model_platform_life_bonus_001","materials":["mat_items_001.json"]},{"name":"model_dynamic_obstacle_box_001","position":[0.6427000164985657,-11.487199783325195,197.0679931640625],"eulerAngles":[180,-17.93000030517578,180],"scale":[0.5,0.5,0.550000011920929],"exportEntity":true,"children":[],"type":"boxObstacle","model":"model_box_obstacle_001","materials":["mat_box_obstacle_001.json"]},{"name":"model_dynamic_obstacle_box_001","position":[-0.6549999713897705,-11.487199783325195,197.0072021484375],"eulerAngles":[180,18.280000686645508,180],"scale":[0.5,0.5,0.5],"exportEntity":true,"children":[],"type":"boxObstacle","model":"model_box_obstacle_001","materials":["mat_box_obstacle_001.json"]},{"name":"model_key_001","position":[0,-10.742199897766113,202.1522979736328],"eulerAngles":[0,0,0],"scale":[1,1,1],"exportEntity":true,"children":[],"type":"key","model":"model_key_001","materials":["mat_items_001.json"]},{"name":"model_finish_001","position":[0,-12.15060043334961,208.40370178222656],"eulerAngles":[180,0,180],"scale":[1.2000000476837158,1.2000000476837158,1.2000000476837158],"exportEntity":true,"children":[],"type":"finishObject","model":"model_finish_001","materials":["mat_gate_001.json","mat_gate_001_teleport.json"]},{"name":"normal_pipe_002","position":[2,0.5,-0.6873999834060669],"eulerAngles":[0,0,0],"scale":[1,1,0.3709999918937683],"exportEntity":true,"children":[],"type":"pipeObject","model":"model_pipe_002","materials":["mat_road_001.json"]},{"name":"normal_pipe_002","position":[-2,0.5,-0.6873999834060669],"eulerAngles":[0,0,0],"scale":[1,1,0.3709999918937683],"exportEntity":true,"children":[],"type":"pipeObject","model":"model_pipe_002","materials":["mat_road_001.json"]},{"name":"normal_pipe_002","position":[-2,0.5,3.75],"eulerAngles":[0,0,0],"scale":[1,1,1],"exportEntity":true,"children":[],"type":"pipeObject","model":"model_pipe_002","materials":["mat_road_001.json"]},{"name":"normal_pipe_002","position":[2,0.5,3.75],"eulerAngles":[0,0,0],"scale":[1,1,1],"exportEntity":true,"children":[],"type":"pipeObject","model":"model_pipe_002","materials":["mat_road_001.json"]},{"name":"normal_pipe_002","position":[-2,0.5,15.726499557495117],"eulerAngles":[0,0,0],"scale":[1,1,1.3799999952316284],"exportEntity":true,"children":[],"type":"pipeObject","model":"model_pipe_002","materials":["mat_road_001.json"]},{"name":"normal_pipe_002","position":[2,0.5,15.726499557495117],"eulerAngles":[0,0,0],"scale":[1,1,1.3799999952316284],"exportEntity":true,"children":[],"type":"pipeObject","model":"model_pipe_002","materials":["mat_road_001.json"]}],"type":"mapObject"}