{"frames": [

{
	"filename": "alarm_pc.png",
	"frame": {"x":1,"y":1,"w":301,"h":301},
	"rotated": false,
	"trimmed": false,
	"spriteSourceSize": {"x":0,"y":0,"w":301,"h":301},
	"sourceSize": {"w":301,"h":301}
},
{
	"filename": "circle_progress_bar_glow_dekstop.png",
	"frame": {"x":304,"y":165,"w":91,"h":88},
	"rotated": false,
	"trimmed": true,
	"spriteSourceSize": {"x":15,"y":97,"w":91,"h":88},
	"sourceSize": {"w":205,"h":205}
},
{
	"filename": "inner_circle_desktop.png",
	"frame": {"x":304,"y":1,"w":176,"h":162},
	"rotated": false,
	"trimmed": true,
	"spriteSourceSize": {"x":15,"y":28,"w":176,"h":162},
	"sourceSize": {"w":205,"h":205}
},
{
	"filename": "shine_desktop.png",
	"frame": {"x":397,"y":165,"w":49,"h":19},
	"rotated": false,
	"trimmed": false,
	"spriteSourceSize": {"x":0,"y":0,"w":49,"h":19},
	"sourceSize": {"w":49,"h":19}
}],
"meta": {
	"app": "https://www.codeandweb.com/texturepacker",
	"version": "1.0",
	"image": "alpha_desktop.png",
	"format": "RGBA8888",
	"size": {"w":481,"h":303},
	"scale": "0.64",
	"smartupdate": "$TexturePacker:SmartUpdate:a7dac5f8c5767a890fd22d63a8679999:3533f827e0f03c729bde9c91371d08a5:4f4a4b7238abc79c99d2c918ad299788$"
}
}
